quaternions/__init__.py
quaternions/quaternion.py
quaternions/rotation.py
quaternions/types.py
quaternions/utils.py
pyquatlib-1.0.0.dist-info/LICENSE
pyquatlib-1.0.0.dist-info/METADATA
pyquatlib-1.0.0.dist-info/WHEEL
pyquatlib-1.0.0.dist-info/entry_points.txt
pyquatlib-1.0.0.dist-info/top_level.txt
pyquatlib-1.0.0.dist-info/RECORD
