Metadata-Version: 2.1
Name: pyquatlib
Version: 1.0.0
Summary: yet another library for quaternions
Home-page: https://github.com/m-bass/pyquatlib
Author: Marco Bosatta
Author-email: mb@xp-obj.com
License: MIT
Platform: UNKNOWN
Classifier: Development Status :: 4 - Beta
Classifier: License :: OSI Approved :: MIT License
Classifier: Programming Language :: Python :: 3
Classifier: Intended Audience :: Science/Research
Classifier: Topic :: Scientific/Engineering
Classifier: Topic :: Scientific/Engineering :: Mathematics
Requires-Python: >=3
Requires-Dist: numpy
Requires-Dist: pandas
Requires-Dist: numba
